monapi/__init__.py
monapi/marketplace.py
monapi_sdk-0.1.4.dist-info/METADATA
monapi_sdk-0.1.4.dist-info/WHEEL
monapi_sdk-0.1.4.dist-info/top_level.txt
monapi_sdk-0.1.4.dist-info/RECORD
