Metadata-Version: 2.4
Name: monapi-sdk
Version: 0.1.4
Summary: SDK for integrating with the Monapi Marketplace
Home-page: https://github.com/yourusername/monapi-sdk
Author: Monapi Team
Author-email: info@monapi.io
Classifier: Programming Language :: Python :: 3
Classifier: Programming Language :: Python :: 3.7
Classifier: Programming Language :: Python :: 3.8
Classifier: Programming Language :: Python :: 3.9
Classifier: License :: OSI Approved :: MIT License
Classifier: Operating System :: OS Independent
Requires-Python: >=3.7
Requires-Dist: fastapi>=0.95.0
Dynamic: author
Dynamic: author-email
Dynamic: classifier
Dynamic: description
Dynamic: description-content-type
Dynamic: home-page
Dynamic: requires-dist
Dynamic: requires-python
Dynamic: summary
